nested_rimraf/__init__.py
nested_rimraf/main.py
nested_rimraf/remove_in_directory.py
nested_rimraf/scan_directory.py
nested_rimraf/utils.py
nested_rimraf-1.0.1.dist-info/entry_points.txt
nested_rimraf-1.0.1.dist-info/LICENSE
nested_rimraf-1.0.1.dist-info/WHEEL
nested_rimraf-1.0.1.dist-info/METADATA
nested_rimraf-1.0.1.dist-info/RECORD
