Metadata-Version: 2.1
Name: nested-rimraf
Version: 1.0.1
Summary: Use it to clear your junk in nested directories Looks for target file/directory through specified tree and then removes everything
Home-page: https://github.com/opa-oz/nested-rimraf
License: GPL-3.0-only
Author: Vladimir Levin
Author-email: opaozhub@gmail.com
Requires-Python: >=3.8,<4.0
Classifier: License :: OSI Approved :: GNU General Public License v3 (GPLv3)
Classifier: Programming Language :: Python :: 3
Classifier: Programming Language :: Python :: 3.10
Classifier: Programming Language :: Python :: 3.8
Classifier: Programming Language :: Python :: 3.9
Requires-Dist: click-spinner (>=0.1.10,<0.2.0)
Requires-Dist: typer[all] (>=0.4.0,<0.5.0)
Project-URL: Documentation, https://github.com/opa-oz/nested-rimraf/blob/main/DOCS.md
Project-URL: Repository, https://github.com/opa-oz/nested-rimraf
